docs/Makefile
docs/conf.py
docs/index.rst
docs/requirements.txt
docs/source/conf.py
docs/source/feast.api.registry.rest.rst
docs/source/feast.api.registry.rst
docs/source/feast.api.rst
docs/source/feast.cli.rst
docs/source/feast.diff.rst
docs/source/feast.dqm.profilers.rst
docs/source/feast.dqm.rst
docs/source/feast.embedded_go.rst
docs/source/feast.infra.common.rst
docs/source/feast.infra.compute_engines.algorithms.rst
docs/source/feast.infra.compute_engines.kubernetes.rst
docs/source/feast.infra.compute_engines.local.backends.rst
docs/source/feast.infra.compute_engines.local.rst
docs/source/feast.infra.compute_engines.rst
docs/source/feast.infra.compute_engines.snowflake.rst
docs/source/feast.infra.compute_engines.spark.rst
docs/source/feast.infra.contrib.rst
docs/source/feast.infra.feature_servers.local_process.rst
docs/source/feast.infra.feature_servers.multicloud.rst
docs/source/feast.infra.feature_servers.rst
docs/source/feast.infra.materialization.contrib.rst
docs/source/feast.infra.materialization.kubernetes.rst
docs/source/feast.infra.materialization.rst
docs/source/feast.infra.mcp_servers.rst
docs/source/feast.infra.offline_stores.contrib.athena_offline_store.rst
docs/source/feast.infra.offline_stores.contrib.athena_offline_store.tests.rst
docs/source/feast.infra.offline_stores.contrib.clickhouse_offline_store.rst
docs/source/feast.infra.offline_stores.contrib.clickhouse_offline_store.tests.rst
docs/source/feast.infra.offline_stores.contrib.couchbase_offline_store.rst
docs/source/feast.infra.offline_stores.contrib.couchbase_offline_store.tests.rst
docs/source/feast.infra.offline_stores.contrib.mssql_offline_store.rst
docs/source/feast.infra.offline_stores.contrib.mssql_offline_store.tests.rst
docs/source/feast.infra.offline_stores.contrib.postgres_offline_store.rst
docs/source/feast.infra.offline_stores.contrib.postgres_offline_store.tests.rst
docs/source/feast.infra.offline_stores.contrib.rst
feast-0.54.0.dist-info/licenses/LICENSE
feast-0.54.0.dist-info/METADATA
feast-0.54.0.dist-info/WHEEL
feast-0.54.0.dist-info/entry_points.txt
feast-0.54.0.dist-info/top_level.txt
feast-0.54.0.dist-info/RECORD
