Metadata-Version: 2.4
Name: feast
Version: 0.54.0
Summary: Python SDK for Feast
Home-page: https://github.com/feast-dev/feast
Author: Feast
License: 
Project-URL: Homepage, https://github.com/feast-dev/feast
Classifier: License :: OSI Approved :: Apache Software License
Classifier: Programming Language :: Python
Classifier: Programming Language :: Python :: 3
Classifier: Programming Language :: Python :: 3.10
Requires-Python: >=3.10.0
License-File: LICENSE
Requires-Dist: click<9.0.0,>=7.0.0
Requires-Dist: colorama<1,>=0.3.9
Requires-Dist: dill~=0.3.0
Requires-Dist: protobuf>=4.24.0
Requires-Dist: Jinja2<4,>=2
Requires-Dist: jsonschema
Requires-Dist: mmh3
Requires-Dist: numpy<3,>=2.0.0
Requires-Dist: pandas<3,>=1.4.3
Requires-Dist: pyarrow<=17.0.0
Requires-Dist: pydantic==2.10.6
Requires-Dist: pygments<3,>=2.12.0
Requires-Dist: PyYAML<7,>=5.4.0
Requires-Dist: requests
Requires-Dist: SQLAlchemy[mypy]>1
Requires-Dist: tabulate<1,>=0.8.0
Requires-Dist: tenacity<9,>=7
Requires-Dist: toml<1,>=0.10.0
Requires-Dist: tqdm<5,>=4
Requires-Dist: typeguard>=4.0.0
Requires-Dist: fastapi>=0.68.0
Requires-Dist: uvicorn[standard]<=0.34.0,>=0.30.6
Requires-Dist: uvicorn-worker
Requires-Dist: gunicorn; platform_system != "Windows"
Requires-Dist: dask[dataframe]>=2024.2.1
Requires-Dist: prometheus_client
Requires-Dist: psutil
Requires-Dist: bigtree>=0.19.2
Requires-Dist: pyjwt
Provides-Extra: aws
Requires-Dist: boto3==1.38.27; extra == "aws"
Requires-Dist: fsspec<=2024.9.0; extra == "aws"
Requires-Dist: aiobotocore<3,>2; extra == "aws"
Provides-Extra: azure
Requires-Dist: azure-storage-blob>=0.37.0; extra == "azure"
Requires-Dist: azure-identity>=1.6.1; extra == "azure"
Requires-Dist: SQLAlchemy>=1.4.19; extra == "azure"
Requires-Dist: pyodbc>=4.0.30; extra == "azure"
Requires-Dist: pymssql<2.3.3; extra == "azure"
Provides-Extra: cassandra
Requires-Dist: cassandra-driver<4,>=3.24.0; extra == "cassandra"
Provides-Extra: clickhouse
Requires-Dist: clickhouse-connect>=0.7.19; extra == "clickhouse"
Provides-Extra: couchbase
Requires-Dist: couchbase==4.3.2; extra == "couchbase"
Requires-Dist: couchbase-columnar==1.0.0; extra == "couchbase"
Provides-Extra: delta
Requires-Dist: deltalake<1.0.0; extra == "delta"
Provides-Extra: docling
Requires-Dist: docling==2.27.0; extra == "docling"
Provides-Extra: duckdb
Requires-Dist: ibis-framework[duckdb]<=9.5.0,>=9.0.0; extra == "duckdb"
Provides-Extra: elasticsearch
Requires-Dist: elasticsearch>=8.13.0; extra == "elasticsearch"
Provides-Extra: faiss
Requires-Dist: faiss-cpu<=1.10.0,>=1.7.0; extra == "faiss"
Provides-Extra: gcp
Requires-Dist: google-api-core<3,>=1.23.0; extra == "gcp"
Requires-Dist: googleapis-common-protos<2,>=1.52.0; extra == "gcp"
Requires-Dist: google-cloud-bigquery[pandas]<4,>=2; extra == "gcp"
Requires-Dist: google-cloud-bigquery-storage<3,>=2.0.0; extra == "gcp"
Requires-Dist: google-cloud-datastore<3,>=2.16.0; extra == "gcp"
Requires-Dist: google-cloud-storage<3,>=1.34.0; extra == "gcp"
Requires-Dist: google-cloud-bigtable<3,>=2.11.0; extra == "gcp"
Requires-Dist: fsspec<=2024.9.0; extra == "gcp"
Provides-Extra: ge
Requires-Dist: great_expectations<1,>=0.15.41; extra == "ge"
Provides-Extra: go
Requires-Dist: cffi>=1.15.0; extra == "go"
Provides-Extra: grpcio
Requires-Dist: grpcio<=1.62.3,>=1.56.2; extra == "grpcio"
Requires-Dist: grpcio-reflection<=1.62.3,>=1.56.2; extra == "grpcio"
Requires-Dist: grpcio-health-checking<=1.62.3,>=1.56.2; extra == "grpcio"
Provides-Extra: hazelcast
Requires-Dist: hazelcast-python-client>=5.1; extra == "hazelcast"
Provides-Extra: hbase
Requires-Dist: happybase<3,>=1.2.0; extra == "hbase"
Provides-Extra: ibis
Requires-Dist: ibis-framework<=9.5.0,>=9.0.0; extra == "ibis"
Requires-Dist: ibis-substrait>=4.0.0; extra == "ibis"
Requires-Dist: poetry-core<2; extra == "ibis"
Requires-Dist: poetry-dynamic-versioning; extra == "ibis"
Provides-Extra: ikv
Requires-Dist: ikvpy>=0.0.36; extra == "ikv"
Provides-Extra: k8s
Requires-Dist: kubernetes; extra == "k8s"
Provides-Extra: image
Requires-Dist: feast[pytorch]; extra == "image"
Requires-Dist: timm>=0.6.0; extra == "image"
Requires-Dist: Pillow>=8.0.0; extra == "image"
Requires-Dist: scikit-learn>=1.0.0; extra == "image"
Provides-Extra: milvus
Requires-Dist: pymilvus==2.4.9; extra == "milvus"
Requires-Dist: milvus-lite==2.4.12; extra == "milvus"
Requires-Dist: feast[setuptools]; extra == "milvus"
Provides-Extra: mssql
Requires-Dist: ibis-framework[mssql]<=9.5.0,>=9.0.0; extra == "mssql"
Provides-Extra: mysql
Requires-Dist: pymysql; extra == "mysql"
Requires-Dist: types-PyMySQL; extra == "mysql"
Provides-Extra: opentelemetry
Requires-Dist: prometheus_client; extra == "opentelemetry"
Requires-Dist: psutil; extra == "opentelemetry"
Provides-Extra: spark
Requires-Dist: pyspark>=4.0.0; extra == "spark"
Provides-Extra: trino
Requires-Dist: trino<0.400.0,>=0.305.0; extra == "trino"
Requires-Dist: regex; extra == "trino"
Provides-Extra: postgres
Requires-Dist: psycopg[binary,pool]==3.2.5; extra == "postgres"
Provides-Extra: postgres-c
Requires-Dist: psycopg[c,pool]==3.2.5; extra == "postgres-c"
Provides-Extra: pytorch
Requires-Dist: torch>=2.7.0; extra == "pytorch"
Requires-Dist: torchvision>=0.22.1; extra == "pytorch"
Provides-Extra: qdrant
Requires-Dist: qdrant-client>=1.12.0; extra == "qdrant"
Provides-Extra: rag
Requires-Dist: transformers>=4.36.0; extra == "rag"
Requires-Dist: datasets>=3.6.0; extra == "rag"
Provides-Extra: ray
Requires-Dist: ray>=2.47.0; python_version == "3.10" and extra == "ray"
Requires-Dist: codeflare-sdk>=0.31.1; python_version != "3.10" and extra == "ray"
Provides-Extra: redis
Requires-Dist: redis<5,>=4.2.2; extra == "redis"
Requires-Dist: hiredis<3,>=2.0.0; extra == "redis"
Provides-Extra: singlestore
Requires-Dist: singlestoredb<1.8.0; extra == "singlestore"
Provides-Extra: snowflake
Requires-Dist: snowflake-connector-python[pandas]<4,>=3.7; extra == "snowflake"
Provides-Extra: sqlite-vec
Requires-Dist: sqlite-vec==v0.1.6; extra == "sqlite-vec"
Provides-Extra: mcp
Requires-Dist: fastapi_mcp; extra == "mcp"
Provides-Extra: ci
Requires-Dist: build; extra == "ci"
Requires-Dist: virtualenv==20.23.0; extra == "ci"
Requires-Dist: cryptography<44,>=43.0; extra == "ci"
Requires-Dist: ruff>=0.8.0; extra == "ci"
Requires-Dist: mypy-protobuf>=3.1; extra == "ci"
Requires-Dist: grpcio-tools<=1.62.3,>=1.56.2; extra == "ci"
Requires-Dist: grpcio-testing<=1.62.3,>=1.56.2; extra == "ci"
Requires-Dist: httpx==0.27.2; extra == "ci"
Requires-Dist: minio==7.2.11; extra == "ci"
Requires-Dist: mock==2.0.0; extra == "ci"
Requires-Dist: moto<5; extra == "ci"
Requires-Dist: mypy<1.11.3,>=1.4.1; extra == "ci"
Requires-Dist: urllib3<3,>=1.25.4; extra == "ci"
Requires-Dist: psutil==5.9.0; extra == "ci"
Requires-Dist: py>=1.11.0; extra == "ci"
Requires-Dist: pytest<8,>=6.0.0; extra == "ci"
Requires-Dist: pytest-asyncio<=0.24.0; extra == "ci"
Requires-Dist: pytest-cov; extra == "ci"
Requires-Dist: pytest-xdist; extra == "ci"
Requires-Dist: pytest-benchmark<4,>=3.4.1; extra == "ci"
Requires-Dist: pytest-lazy-fixture==0.6.3; extra == "ci"
Requires-Dist: pytest-timeout==1.4.2; extra == "ci"
Requires-Dist: pytest-ordering~=0.6.0; extra == "ci"
Requires-Dist: pytest-mock==1.10.4; extra == "ci"
Requires-Dist: pytest-env; extra == "ci"
Requires-Dist: Sphinx<7,>4.0.0; extra == "ci"
Requires-Dist: sqlglot[rs]>=23.4; extra == "ci"
Requires-Dist: testcontainers==4.9.0; extra == "ci"
Requires-Dist: python-keycloak==4.2.2; extra == "ci"
Requires-Dist: pre-commit<3.3.2; extra == "ci"
Requires-Dist: assertpy==1.1; extra == "ci"
Requires-Dist: pip-tools; extra == "ci"
Requires-Dist: pybindgen==0.22.0; extra == "ci"
Requires-Dist: types-protobuf~=3.19.22; extra == "ci"
Requires-Dist: python-dateutil==2.9.0; extra == "ci"
Requires-Dist: types-python-dateutil; extra == "ci"
Requires-Dist: types-pytz; extra == "ci"
Requires-Dist: types-PyYAML; extra == "ci"
Requires-Dist: types-redis; extra == "ci"
Requires-Dist: types-requests<2.31.0; extra == "ci"
Requires-Dist: types-setuptools; extra == "ci"
Requires-Dist: types-tabulate; extra == "ci"
Requires-Dist: virtualenv<20.24.2; extra == "ci"
Requires-Dist: feast[aws,azure,cassandra,clickhouse,couchbase,delta,docling,duckdb,elasticsearch,faiss,gcp,ge,go,grpcio,hazelcast,hbase,ibis,ikv,image,k8s,mcp,milvus,mssql,mysql,opentelemetry,postgres,pytorch,qdrant,rag,ray,redis,singlestore,snowflake,spark,sqlite_vec,trino]; extra == "ci"
Provides-Extra: nlp
Requires-Dist: feast[docling,image,milvus,pytorch,rag]; extra == "nlp"
Provides-Extra: dev
Requires-Dist: feast[ci]; extra == "dev"
Provides-Extra: docs
Requires-Dist: feast[ci]; extra == "docs"
Provides-Extra: minimal
Requires-Dist: feast[aws,duckdb,gcp,go,grpcio,k8s,mcp,milvus,mysql,opentelemetry,postgres-c,redis,snowflake]; extra == "minimal"
Provides-Extra: minimal-sdist-build
Requires-Dist: feast[minimal]; extra == "minimal-sdist-build"
Requires-Dist: feast[ibis]; extra == "minimal-sdist-build"
Requires-Dist: meson<1.7.2; extra == "minimal-sdist-build"
Requires-Dist: pybindgen==0.22.0; extra == "minimal-sdist-build"
Requires-Dist: sphinx!=4.0.0; extra == "minimal-sdist-build"
Requires-Dist: types_psutil<7.0.0.20250401; extra == "minimal-sdist-build"
Requires-Dist: greenlet!=0.4.17; extra == "minimal-sdist-build"
Requires-Dist: meson-python<0.16.0,>=0.15.0; extra == "minimal-sdist-build"
Requires-Dist: Cython<3.1,>=0.29.34; extra == "minimal-sdist-build"
Requires-Dist: flit_core<4,>=3.8; extra == "minimal-sdist-build"
Requires-Dist: patchelf>=0.11.0; extra == "minimal-sdist-build"
Requires-Dist: scikit-build-core>=0.10; extra == "minimal-sdist-build"
Requires-Dist: hatch-fancy-pypi-readme>=23.2.0; extra == "minimal-sdist-build"
Requires-Dist: hatch-vcs==0.4.0; extra == "minimal-sdist-build"
Requires-Dist: hatchling<2,>=1.6.0; extra == "minimal-sdist-build"
Requires-Dist: calver<2025.4.1; extra == "minimal-sdist-build"
Provides-Extra: setuptools
Requires-Dist: setuptools<81,>=60; extra == "setuptools"
Dynamic: home-page
Dynamic: license-file
Dynamic: requires-python
